vtc_scrypt_new.cp39-win32.pyd
vtc_scrypt_new_test-0.0.1.dist-info/METADATA
vtc_scrypt_new_test-0.0.1.dist-info/WHEEL
vtc_scrypt_new_test-0.0.1.dist-info/top_level.txt
vtc_scrypt_new_test-0.0.1.dist-info/RECORD
